paretointel/__init__.py
paretointel/hdi/__init__.py
paretointel/hdi/hdi.py
paretointel/hdi/db/__init__.py
paretointel/hdi/db/db.py
paretointel/hdi/spark/__init__.py
paretointel/hdi/spark/logging.py
paretointel/hdi/spark/spark.py
paretointel-0.1.1.dist-info/METADATA
paretointel-0.1.1.dist-info/WHEEL
paretointel-0.1.1.dist-info/top_level.txt
paretointel-0.1.1.dist-info/RECORD
