Metadata-Version: 2.1
Name: paretointel
Version: 0.1.1
Summary: Pareto Engineering Python libraries
Home-page: https://github.com/paretointel/pareto-py
Author: Pareto Intelligence
Author-email: engineering@paretointel.com
License: UNKNOWN
Platform: UNKNOWN
